SympNetsTorch/SympNets.py
SympNetsTorch/__init__.py
sympnetstorch-0.0.2.dist-info/METADATA
sympnetstorch-0.0.2.dist-info/WHEEL
sympnetstorch-0.0.2.dist-info/licenses/LICENSE
sympnetstorch-0.0.2.dist-info/RECORD
