Metadata-Version: 2.4
Name: SympNetsTorch
Version: 0.0.2
Summary: Symplectic PyTorch Modules
Project-URL: Homepage, https://github.com/MSU-Beam-Dynamics/SympNetsTorch
Project-URL: Bug Tracker, https://github.com/MSU-Beam-Dynamics/SympNetsTorch/issues
Author-email: Kelly Anderson <kjanderson24@proton.me>
License:                     GNU GENERAL PUBLIC LICENSE
License-File: LICENSE
Classifier: License :: OSI Approved :: GNU General Public License v3 (GPLv3)
Classifier: License :: OSI Approved :: GNU General Public License v3 or later (GPLv3+)
Classifier: Programming Language :: Python :: 3
Classifier: Programming Language :: Python :: 3.10
Classifier: Programming Language :: Python :: 3.11
Requires-Python: >=3.10
Requires-Dist: torch
